cwmetrics/__init__.py
cloudwatch_metrics_buffer-0.1.0.dist-info/LICENSE
cloudwatch_metrics_buffer-0.1.0.dist-info/METADATA
cloudwatch_metrics_buffer-0.1.0.dist-info/WHEEL
cloudwatch_metrics_buffer-0.1.0.dist-info/top_level.txt
cloudwatch_metrics_buffer-0.1.0.dist-info/RECORD
