Metadata-Version: 2.1
Name: cloudwatch-metrics-buffer
Version: 0.1.0
Summary: Library for posting metrics to AWS CloudWatch
Home-page: https://github.com/kecabojan/cloudwatch-metrics-buffer
Author: Bojan Keca
Author-email: kecabojan@gmail.com
License: MIT
Platform: UNKNOWN
Classifier: License :: OSI Approved :: MIT License
Classifier: Programming Language :: Python :: 3
Classifier: Programming Language :: Python :: 3.7
Requires-Dist: boto3
Requires-Dist: botocore
